dewloosh/core/__init__.py
dewloosh/core/abc.py
dewloosh/core/acp.py
dewloosh/core/attr.py
dewloosh/core/colors.py
dewloosh/core/cp.py
dewloosh/core/decorate.py
dewloosh/core/downloads.py
dewloosh/core/infix.py
dewloosh/core/io.py
dewloosh/core/meta.py
dewloosh/core/osutils.py
dewloosh/core/signature.py
dewloosh/core/testing.py
dewloosh/core/typing.py
dewloosh/core/warning.py
dewloosh/core/wrapping.py
dewloosh/core/tools/__init__.py
dewloosh/core/tools/alphabet.py
dewloosh/core/tools/kwargtools.py
dewloosh/core/tools/tools.py
dewloosh.core-1.0.21.dist-info/LICENSE
dewloosh.core-1.0.21.dist-info/METADATA
dewloosh.core-1.0.21.dist-info/WHEEL
dewloosh.core-1.0.21.dist-info/top_level.txt
dewloosh.core-1.0.21.dist-info/RECORD
