Metadata-Version: 2.1
Name: dewloosh.core
Version: 1.0.21
Summary: Common developer utilities and base classes to support other dewloosh packages.
Home-page: https://github.com/dewloosh/dewloosh-core
Download-URL: https://github.com/dewloosh/dewloosh-core/archive/refs/tags/1.0.21.zip
Author: Bence Balogh
Author-email: dewloosh@gmail.com
Classifier: Development Status :: 5 - Production/Stable
Classifier: License :: OSI Approved :: MIT License
Classifier: Programming Language :: Python :: 3.7
Classifier: Programming Language :: Python :: 3.8
Classifier: Programming Language :: Python :: 3.9
Classifier: Programming Language :: Python :: 3.10
Classifier: Programming Language :: Python :: 3 :: Only
Classifier: Operating System :: OS Independent
Requires-Python: >=3.7, <3.11
License-File: LICENSE
Requires-Dist: setuptools (>=65.5.1)
Requires-Dist: wheel (>=0.38.0)
Requires-Dist: appdirs
Requires-Dist: matplotlib
Requires-Dist: numpy (>=1.21.0rc1)
